_tree_parser.cpython-36m-darwin.so
tests/__init__.py
tests/test_abundance.py
tests/test_annotate_extra.py
tests/test_assign.py
tests/test_clade_annotation.py
tests/test_clade_exclusion_evaluator.py
tests/test_classy.py
tests/test_commands.py
tests/test_create_refpkg.py
tests/test_entish.py
tests/test_entrez_utils.py
tests/test_external_command_interface.py
tests/test_fasta.py
tests/test_file_parsers.py
tests/test_graftm_utils.py
tests/test_hmmer_parser.py
tests/test_jplace_utils.py
tests/test_lca_calculations.py
tests/test_logger.py
tests/test_mcc_calculator.py
tests/test_phylo_cluster.py
tests/test_phylo_seq.py
tests/test_phylogeny_painting.py
tests/test_placement_trainer.py
tests/test_refpkg.py
tests/test_rel_evo_dist.py
tests/test_seq_clustering.py
tests/test_taxonomic_hierarchy.py
tests/test_training_utils.py
tests/test_treesapp.py
tests/test_update_refpkg.py
tests/test_utilities.py
tests/test_wrapper.py
tests/testing_utils.py
treesapp/__init__.py
treesapp/__main__.py
treesapp/abundance.py
treesapp/annotate_extra.py
treesapp/assign.py
treesapp/clade_annotation.py
treesapp/clade_exclusion_evaluator.py
treesapp/classy.py
treesapp/commands.py
treesapp/create_refpkg.py
treesapp/entish.py
treesapp/entrez_utils.py
treesapp/external_command_interface.py
treesapp/fasta.py
treesapp/file_parsers.py
treesapp/graftm_utils.py
treesapp/hmmer_tbl_parser.py
treesapp/jplace_utils.py
treesapp/lca_calculations.py
treesapp/logger.py
treesapp/mcc_calculator.py
treesapp/phylo_cluster.py
treesapp/phylo_dist.py
treesapp/phylo_seq.py
treesapp/phylogeny_painting.py
treesapp/placement_trainer.py
treesapp/refpkg.py
treesapp/rel_evo_dist.py
treesapp/seq_clustering.py
treesapp/taxonomic_hierarchy.py
treesapp/training_utils.py
treesapp/treesapp_args.py
treesapp/update_refpkg.py
treesapp/utilities.py
treesapp/wrapper.py
treesapp/data/DsrAB_build.pkl
treesapp/data/HydA_build.pkl
treesapp/data/McrA_build.pkl
treesapp/data/McrB_build.pkl
treesapp/data/McrG_build.pkl
treesapp/data/NapA_build.pkl
treesapp-0.11.4.dist-info/LICENSE
treesapp-0.11.4.dist-info/METADATA
treesapp-0.11.4.dist-info/WHEEL
treesapp-0.11.4.dist-info/entry_points.txt
treesapp-0.11.4.dist-info/top_level.txt
treesapp-0.11.4.dist-info/RECORD
