Metadata-Version: 2.1
Name: treesapp
Version: 0.11.4
Summary: TreeSAPP is a functional and taxonomic annotation tool for genomes and metagenomes.
Home-page: https://github.com/hallamlab/TreeSAPP
Author: Connor Morgan-Lang
Author-email: c.morganlang@gmail.com
License: GPL-3.0
Platform: UNKNOWN
Classifier: Environment :: Console
Classifier: Intended Audience :: Science/Research
Classifier: License :: OSI Approved :: GNU General Public License v3 (GPLv3)
Classifier: Natural Language :: English
Classifier: Operating System :: POSIX :: Linux
Classifier: Operating System :: MacOS :: MacOS X
Classifier: Programming Language :: C++
Classifier: Programming Language :: Python :: 3.6
Classifier: Programming Language :: Python :: 3.7
Classifier: Programming Language :: Python :: 3.8
Classifier: Topic :: Scientific/Engineering :: Bio-Informatics
Classifier: Development Status :: 5 - Production/Stable
License-File: LICENSE
Requires-Dist: biopython (>=1.78)
Requires-Dist: ete3 (>=3.1.2)
Requires-Dist: joblib (==1.0.0)
Requires-Dist: numpy (>=1.19.2)
Requires-Dist: packaging (>=20.4)
Requires-Dist: pyfastx (>=0.8.2)
Requires-Dist: pygtrie (>=2.3.3)
Requires-Dist: samsum (>=0.1.4)
Requires-Dist: scikit-learn (~=0.24.2)
Requires-Dist: scipy (>=1.5.2)
Requires-Dist: six (>=1.15.0)
Requires-Dist: seaborn (>=0.11.0)
Requires-Dist: tqdm (>=4.50.0)
Requires-Dist: pytest (>=6.2.5)
Requires-Dist: pandas (>=1.1.0)
Requires-Dist: matplotlib (>=3.3.0)
Provides-Extra: test
Requires-Dist: pytest ; extra == 'test'
Requires-Dist: pytest-cov ; extra == 'test'
